{"auctionId":"6051","Посада:":"ліцитатор","П.І.П:":"Борисова Наталія Сергіївна","Контактний телефон:":"(057)717-11-83","Отримувач":"Комунальне підприємство Харківської обласної ради \"ОБЛЗЕМПРОЕКТ\"","Код отримувача (ЄДПРОУ)":"37875212","Банк отримувача для сплати гарантійного внеску":"ПАТ \"БАНК \"ГРАНД\" у відд. № 19","Код банку отримувача (МФО) для сплати гарантійного внеску":"351607","Рахунок отримувача для сплати гарантійного внеску":"2600081971848","Банк отримувача для сплати реєстраційного внеску":"ПАТ \"БАНК \"ГРАНД\" у відд. № 19","Код банку отримувача (МФО) для сплати реєстраційного внеску":"351607","Рахунок отримувача для сплати реєстраційного внеску":"2600081971848","Найменування організатора земельних торгів:":"Харківська обласна державна адміністрація","Кадастровий номер:":"6321256000:02:000:0043","Місце розташування:":"Харківська область, Валківський район, Старомерчицька селищна рада","Площа земельної ділянки:":"82.3277","Цільове призначення земельної ділянки:":"Для ведення товарного сільськогосподарського виробництва","Містобудівні потреби (види використання):":"використовувати за цільовим призначенням","Договір:":"Оренди","Умови  договору, який укладається на земельних торгах:":"Строк користування земельною ділянкою 25 років","Стартовий розмір річної плати за користування земельною ділянкою (грн):":"172130.59","Містобудівні умови земельної ділянки:":"відсутні","Час проведення земельних торгів:":"04.11.2016 10:00","Місце проведення земельних торгів:":"Харківська область, Харків район, м. Харків;вул. Мельникова, б. 2, к. 21","Обмеження забудови земельної ділянки:":"відсутні","Розмір реєстраційного внеску:":"725.00","Розмір гарантійного внеску:":"8606.53","Порядок сплати внесків:":"до 28 жовтня 2016 року","Розмір річної плати за користування земельною ділянкою:":"416555.19","Строк користування земельною ділянкою:":"25"}