{"auctionId":"1121","Посада:":"Генеральний директор","П.І.П:":"Крамаренко Леонід Віталійович","Контактний телефон:":"0522245822  ","Отримувач":"Товарна біржа «Кіровоградська аграрна біржа»","Код отримувача (ЄДПРОУ)":"31008446","Банк отримувача для сплати гарантійного внеску":"ЦФ ПАТ «Кредобанк», м. Львів","Код банку отримувача (МФО) для сплати гарантійного внеску":"325365","Рахунок отримувача для сплати гарантійного внеску":"2600601899054","Банк отримувача для сплати реєстраційного внеску":"ЦФ ПАТ «Кредобанк», м. Львів","Код банку отримувача (МФО) для сплати реєстраційного внеску":"325365","Рахунок отримувача для сплати реєстраційного внеску":"2600702899054","Найменування організатора земельних торгів:":"Добровеличківська селищна рада, Кіровоградської області","Кадастровий номер:":"3521755100:50:038:0002","Місце розташування:":"Кіровоградська область, Добровеличківський район, смт Добровеличківка, вулиця Леніна","Площа земельної ділянки:":"0.0033","Цільове призначення земельної ділянки:":"для розміщення об\"єкту торгівлі","Містобудівні потреби (види використання):":"відсутні","Договір:":"Оренди","Умови  договору, який укладається на земельних торгах:":"викладені в тексті договору, що пропонується укласти між Організатором та Переможцем в день торгів","Стартовий розмір річної плати за користування земельною ділянкою (грн):":"831.96","Містобудівні умови земельної ділянки:":"згідно вимог і обмежень , зазначених у  висновках погоджувальних організацій","Час проведення земельних торгів:":"12.05.2014 11:00","Місце проведення земельних торгів:":"Кіровоградська область, Добровеличківський район, с.м.т. Добровеличківка;вул. Шевченка, 132, Добровеличківська селищна рада, смт. Добровеличківка, Кіровоградська обл.","Обмеження забудови земельної ділянки:":"відсутні","Розмір реєстраційного внеску:":"609.00","Розмір гарантійного внеску:":"41.60","Порядок сплати внесків:":"Отримувач: ТБ «Кіровоградська аграрна біржа», для сплати реєстраційного внеску р/р 2600702899054 в ЦФ ПАТ «Кредобанк», м. Львів, МФО 325365, для сплати гарантійного внеску р/р 2600601899054 в ЦФ ПАТ «Кредобанк», м. Львів, МФО 325365, код ЄДРПОУ 31008446\r\n","Розмір річної плати за користування земельною ділянкою:":"843.96","Строк користування земельною ділянкою:":"10"}