{"auctionId":"9866","Посада:":"Начальник відділу КВП","П.І.П:":"Компанець Тетяна Вячеславівна","Контактний телефон:":"(0532) 50-04-15 050-78-40-549","Отримувач":"ПП \"ІМАКО\"","Код отримувача (ЄДПРОУ)":"36680914","Банк отримувача для сплати гарантійного внеску":"ПАТ \"КРЕДІ АГРІКОЛЬ БАНК\" м. Київ","Код банку отримувача (МФО) для сплати гарантійного внеску":"300614","Рахунок отримувача для сплати гарантійного внеску":"26000500231849","Банк отримувача для сплати реєстраційного внеску":"ПАТ \"АЛЬФА-БАНК\"","Код банку отримувача (МФО) для сплати реєстраційного внеску":"300346","Рахунок отримувача для сплати реєстраційного внеску":"26003018484701","Найменування організатора земельних торгів:":"Горішньоплавнівська міська рада","Кадастровий номер:":"5310200000:50:028:0359","Місце розташування:":"Полтавська область, м. Комсомольськ, вулиця Миру","Площа земельної ділянки:":"0.3861","Цільове призначення земельної ділянки:":"Для будівництва і обслуговування багатоквартирного житлового будинку","Містобудівні потреби (види використання):":"Житлової забудови і громадського призначення.","Договір:":"Оренди","Умови  договору, який укладається на земельних торгах:":"Термін оренди - 3 роки. З текстом договору оренди можна ознайомитися у вкладених файлах. Сума витрат (видатків), що підлягає відшкодуванню переможцем: 2433,26 грн. - витрати на підготовку земельних торгів (згідно кошторису); 50% від кінцевого розміру річн","Стартовий розмір річної плати за користування земельною ділянкою (грн):":"94513.87","Містобудівні умови земельної ділянки:":"Згідно проекту землеустрою.","Час проведення земельних торгів:":"19.12.2017 11:00","Місце проведення земельних торгів:":"Полтавська область, Комсомольськ район, м. Комсомольськ;вул. Миру, будинок 24, місто Горішні Плавні (м. Комсомольськ)","Обмеження забудови земельної ділянки:":"Згідно проекту землеустрою.","Розмір реєстраційного внеску:":"840.00","Розмір гарантійного внеску:":"4725.69","Порядок сплати внесків:":"Із дня розміщення інформації на сайті Держгеокадастру до 17:00 години 13 грудня 2017 року (до подання заяви на участь у торгах).","Розмір річної плати за користування земельною ділянкою:":"120032.65","Строк користування земельною ділянкою:":"3"}