{"auctionId":"10761","Посада:":"заступник генерального директора","П.І.П:":"Цифуляк Оксана Іванівна","Контактний телефон:":"(032) 2443092, моб.+380961315421","Отримувач":"ПП \"Фірма \"СОМГІЗ\"","Код отримувача (ЄДПРОУ)":"20810095","Банк отримувача для сплати гарантійного внеску":"ПАТ\"ВіЕс Банк\"","Код банку отримувача (МФО) для сплати гарантійного внеску":"325213","Рахунок отримувача для сплати гарантійного внеску":"26000000013209","Банк отримувача для сплати реєстраційного внеску":"ПАТ\"ВіЕс Банк\"","Код банку отримувача (МФО) для сплати реєстраційного внеску":"325213","Рахунок отримувача для сплати реєстраційного внеску":"26004000001347","Найменування організатора земельних торгів:":"Головне управління Держгеокадастру у Волинській області","Кадастровий номер:":"0725587600:07:001:0716","Місце розташування:":"Волинська область, Турійський район, за межами населених пунктів Туличівської сільської ради","Площа земельної ділянки:":"12.0000","Цільове призначення земельної ділянки:":"А.01.01","Містобудівні потреби (види використання):":" для ведення товарного сільськогосподарського виробництва","Договір:":"Оренди","Умови  договору, який укладається на земельних торгах:":"Договір оренди земельної ділянки укладається між організатором земельних торгів і переможцем безпосередньо в день проведення торгів (детальніше дивитись в проекті договору у вкладених файлах)","Стартовий розмір річної плати за користування земельною ділянкою (грн):":"13823.48","Містобудівні умови земельної ділянки:":"не визначені","Час проведення земельних торгів:":"21.03.2018 10:00","Місце проведення земельних торгів:":"Волинська область, Луцьк район, м. Луцьк;вул. Ківерцівська, 1а, офіс, 1","Обмеження забудови земельної ділянки:":"не зареєстровані","Розмір реєстраційного внеску:":"881.00","Розмір гарантійного внеску:":"691.17","Порядок сплати внесків:":"до 16 год. 30 хв. 15 березня 2018 року (включно); переможцем торгів сплачуються кошти: за підготовку лота в сумі 23223,85 гривень; за організацію та проведення торгів 50% від вартості продажу лота (детальніше дивитися інформацію у вкладених файлах)","Розмір річної плати за користування земельною ділянкою:":"13961.48","Строк користування земельною ділянкою:":"7"}