{"auctionId":"11112","Посада:":"відповідальна особа","П.І.П:":"Романко Р.М.","Контактний телефон:":"+380509871769","Отримувач":"ФОП Романко Роман Миколайович","Код отримувача (ЄДПРОУ)":"3012518013","Банк отримувача для сплати гарантійного внеску":"АТ \"Ощадбанк\"","Код банку отримувача (МФО) для сплати гарантійного внеску":"356334","Рахунок отримувача для сплати гарантійного внеску":"26000501481223","Банк отримувача для сплати реєстраційного внеску":"АТ \"Ощадбанк\"","Код банку отримувача (МФО) для сплати реєстраційного внеску":"356334","Рахунок отримувача для сплати реєстраційного внеску":"26001500481223","Найменування організатора земельних торгів:":"Головне управління Держгеокадастру у Чернівецькій області","Кадастровий номер:":"7324586500:03:005:0874","Місце розташування:":"Чернівецька область, Сторожинецький район, Михальчанська сільська рада, вулиця Сторожинецька","Площа земельної ділянки:":"0.0200","Цільове призначення земельної ділянки:":"Для ведення особистого селянського господарства","Містобудівні потреби (види використання):":"для ведення особистого селянського господарства","Договір:":"Оренди","Умови  договору, який укладається на земельних торгах:":"термін оренди 7 років","Стартовий розмір річної плати за користування земельною ділянкою (грн):":"5.62","Містобудівні умови земельної ділянки:":"використовувати за цільовим призначенням","Час проведення земельних торгів:":"17.04.2018 10:00","Місце проведення земельних торгів:":"Чернівецька область, Сторожинецький район, с. Михальча;м. Чернівці, вул. Героїв Майдану, 194-А, приміщення Головного управління Держгеокадастру у Чернівецькій області","Обмеження забудови земельної ділянки:":"відсутні","Розмір реєстраційного внеску:":"880.00","Розмір гарантійного внеску:":"0.28","Порядок сплати внесків:":"1. «Реєстраційний внесок 880,00грн., в т.ч.ПДВ-20%»; 2. «Гарантійний внесок 0,28 грн. без ПДВ ». Прийом заяв та документів з 14.30 до 17.30 год. до 11.04.18р. включно","Розмір річної плати за користування земельною ділянкою:":"700.03","Строк користування земельною ділянкою:":"7"}