{"auctionId":"11438","Посада:":"директор","П.І.П:":"Ніцевич Тимур Валерійович","Контактний телефон:":"(0382) 70-69-36, (0382) 65-25-32","Отримувач":"ЗАЦ «Карат»","Код отримувача (ЄДПРОУ)":"23832648","Банк отримувача для сплати гарантійного внеску":"АТ «УКРСИББАНК» м. Харків","Код банку отримувача (МФО) для сплати гарантійного внеску":"351005","Рахунок отримувача для сплати гарантійного внеску":"26003198531700","Банк отримувача для сплати реєстраційного внеску":"АТ «УКРСИББАНК» м. Харків","Код банку отримувача (МФО) для сплати реєстраційного внеску":"351005","Рахунок отримувача для сплати реєстраційного внеску":"26002198531701","Найменування організатора земельних торгів:":"Головне управління Держгеокадастру у Хмельницькій області","Кадастровий номер:":"6822182200:06:006:0101","Місце розташування:":"Хмельницька область, Ізяславський район, Дертківська сільська рада","Площа земельної ділянки:":"29.2468","Цільове призначення земельної ділянки:":"Для ведення товарного сільськогосподарського виробництва","Містобудівні потреби (види використання):":"Для ведення товарного сільськогосподарського виробництва","Договір:":"Оренди","Умови  договору, який укладається на земельних торгах:":"Договір оренди укладається терміном на 7 (сім) років. Витрати у сумі 7131,60 грн, здійснені Виконавцем на підготовку лоту, відшкодовуються Переможцем земельних торгів.","Стартовий розмір річної плати за користування земельною ділянкою (грн):":"18865.41","Містобудівні умови земельної ділянки:":"Відсутні","Час проведення земельних торгів:":"08.05.2018 10:00","Місце проведення земельних торгів:":"Хмельницька область, Хмельницький район, м. Хмельницький;вул. Інститутська, 4/1. Приміщення Головного управління Держгеокадастру у Хмельницькій області, 5 поверх (актовий зал).","Обмеження забудови земельної ділянки:":"Відсутні","Розмір реєстраційного внеску:":"881.00","Розмір гарантійного внеску:":"943.27","Порядок сплати внесків:":"Сплачується на відкриті рахунки виконавця земельних торгів. Документи приймаються до 02.05.2018 року включно.","Розмір річної плати за користування земельною ділянкою:":"19241.41","Строк користування земельною ділянкою:":"7"}