{"auctionId":"329","Посада:":"Президент  ТБ \"УЗТБ \"Придніпровська\"","П.І.П:":"Кузякін С.І.","Контактний телефон:":"050-143-555-3","Отримувач":"ТБ \"УЗТБ \"Придніпровська\" ","Код отримувача (ЄДПРОУ)":"35249588","Банк отримувача для сплати гарантійного внеску":"АТ \"Дельта Банк\"","Код банку отримувача (МФО) для сплати гарантійного внеску":"380236","Рахунок отримувача для сплати гарантійного внеску":"26007002009949","Банк отримувача для сплати реєстраційного внеску":"АТ \"Дельта Банк\"","Код банку отримувача (МФО) для сплати реєстраційного внеску":"380236","Рахунок отримувача для сплати реєстраційного внеску":"26007002009949","Найменування організатора земельних торгів:":"Узинська міська рада","Кадастровий номер:":"3220410500:02:020:0081","Місце розташування:":"Київська область, Білоцерківський район, м.Узин, площа Г.Космосу, 1","Площа земельної ділянки:":"0.1181","Цільове призначення земельної ділянки:":"03.07","Містобудівні потреби (види використання):":"для будівництва та обслуговування будівель торгівлі","Договір:":"Купівлі-продажу","Умови  договору, який укладається на земельних торгах:":"Відповідно до договору купівлі-продажу (у вкладених матеріалах)","Стартова ціна продажу земельної ділянки (грн):":"60892.00","Містобудівні умови земельної ділянки:":"При проектуванні та будівництві об'єктів містобудування дотримуватися містобудівних умов і обмежень забудови земельних ділянок","Час проведення земельних торгів:":"13.09.2013 10:00","Місце проведення земельних торгів:":"Київська область, Білоцерківський район, м. Узин;Київська область, Білоцерківськкий р-н, м. Узин, вул. Жовтнева 16/1","Обмеження забудови земельної ділянки:":"Відповідно до вкладених файлів","Розмір реєстраційного внеску:":"570.00","Розмір гарантійного внеску:":"3044.60","Порядок сплати внесків:":"Реєстраційні та гарантійні внески сплачуються на рахунок виконавця торгів. Документи, що підтверджують сплату, подаються в день подання заяви на участь у земельних торгах","Ціна продажу земельної ділянки:":"62109.84"}