{"auctionId":"14036","Посада:":"Директор","П.І.П:":"Деркач Олег Анатолійович","Контактний телефон:":"097-762-45-96","Отримувач":"ПП «ЗЕМТОРГ»","Код отримувача (ЄДПРОУ)":"42395577","Банк отримувача для сплати гарантійного внеску":"АТ КБ \"ПРИВАТБАНК\"","Код банку отримувача (МФО) для сплати гарантійного внеску":"354347","Рахунок отримувача для сплати гарантійного внеску":"26002051537769","Банк отримувача для сплати реєстраційного внеску":"АТ КБ \"ПРИВАТБАНК\"","Код банку отримувача (МФО) для сплати реєстраційного внеску":"354347","Рахунок отримувача для сплати реєстраційного внеску":"26008051546475","Найменування організатора земельних торгів:":"ДАШУКІВСЬКА СІЛЬСЬКА РАДА ","Кадастровий номер:":"7122882800:02:000:0018","Місце розташування:":"Черкаська область, Лисянський район, с. Дашуківка","Площа земельної ділянки:":"2.9277","Цільове призначення земельної ділянки:":"Для ведення товарного сільськогосподарського виробництва","Містобудівні потреби (види використання):":"Відсутні","Договір:":"Оренди","Умови  договору, який укладається на земельних торгах:":"Строк оренди – 8 років. Переможець торгів сплачує винагороду виконавцю у розмірі 50% річної плати за користування земельною ділянкою, але не більше 2000 неопод.мін. доходів громадян","Стартовий розмір річної плати за користування земельною ділянкою (грн):":"14190.12","Містобудівні умови земельної ділянки:":"Відсутні","Час проведення земельних торгів:":"09.11.2018 11:00","Місце проведення земельних торгів:":"Черкаська область, Лисянський район, с. Дашуківка;с. Дашуківка, вул. Ювілейна, 30, Лисянський р-н. Черкаська обл. (приміщення сільської ради, актовий зал)","Обмеження забудови земельної ділянки:":"Відсутні","Розмір реєстраційного внеску:":"850.00","Розмір гарантійного внеску:":"709.51","Порядок сплати внесків:":"до 16:00 год. 05 листопада 2018 р.","Розмір річної плати за користування земельною ділянкою:":"18021.42","Строк користування земельною ділянкою:":"8"}