{"auctionId":"15693","Посада:":"аукціоніст","П.І.П:":"Мацьоцький О.І.","Контактний телефон:":"+380506726797","Отримувач":"ДП \"Буковинська управляюча компанія\"","Код отримувача (ЄДПРОУ)":"14263625","Банк отримувача для сплати гарантійного внеску":"ЧФ АТ КБ \"ПриватБанк\" ","Код банку отримувача (МФО) для сплати гарантійного внеску":"356282","Рахунок отримувача для сплати гарантійного внеску":"26005051512797","Банк отримувача для сплати реєстраційного внеску":"ЧФ АТ КБ \"Приватбанк\"","Код банку отримувача (МФО) для сплати реєстраційного внеску":"356282","Рахунок отримувача для сплати реєстраційного внеску":"26004051600774","Найменування організатора земельних торгів:":"Коровійська сільська рада","Кадастровий номер:":"7321082700:01:003:0747","Місце розташування:":"Чернівецька область, Глибоцький район, с. Коровія","Площа земельної ділянки:":"0.1974","Цільове призначення земельної ділянки:":"03.10","Містобудівні потреби (види використання):":"для будівництва та обслуговування будівель ринкової інфраструктури","НГО земельної ділянки, (грн):":"690959.22","Договір:":"Оренди","Умови  договору, який укладається на земельних торгах:":"термін оренди 10 років","Стартовий розмір річної плати за користування земельною ділянкою (грн):":"34547.96","Містобудівні умови земельної ділянки:":"використовувати за цільовим призначенням","Час проведення земельних торгів:":"26.02.2019 14:00","Місце проведення земельних торгів:":"Чернівецька область, Глибоцький район, с. Коровія;вул. Головна, 78 (приміщення сільської ради)","Обмеження забудови земельної ділянки:":"відсутні","Розмір реєстраційного внеску:":"960.50","Розмір гарантійного внеску:":"1727.40","Порядок сплати внесків:":"1. «Реєстраційний внесок 960,50грн., без ПДВ»; 2. «Гарантійний внесок 1727,40 грн. без ПДВ ». Прийом заяв та документів до 15-00 год. до 25.01.19р. включно.","Розмір річної плати за користування земельною ділянкою:":"35929.88","Строк користування земельною ділянкою:":"10"}