{"auctionId":"18154","Посада:":"директор","П.І.П:":"Молот Геннадій Миколайович","Контактний телефон:":"64-00-84, 067 460 22 77","Отримувач":"ПП \" Десна-Експерт-М\"","Код отримувача (ЄДПРОУ)":"33111200","Банк отримувача для сплати гарантійного внеску":"ПАТ «Полікомбанк» м. Чернігова","Код банку отримувача (МФО) для сплати гарантійного внеску":"353100","Рахунок отримувача для сплати гарантійного внеску":"26009118673","Банк отримувача для сплати реєстраційного внеску":"ПАТ «Полікомбанк» м. Чернігова","Код банку отримувача (МФО) для сплати реєстраційного внеску":"353100","Рахунок отримувача для сплати реєстраційного внеску":"26002018673","Найменування організатора земельних торгів:":"Головне управління Держгеокадастру у Сумській області","Кадастровий номер:":"5922986900:05:002:0270","Місце розташування:":"Сумська область, Лебединський район, Московськобобрицька сільська рада","Площа земельної ділянки:":"39.8090","Цільове призначення земельної ділянки:":"Для ведення товарного сільськогосподарського виробництва","Містобудівні потреби (види використання):":"не встановлені.   ","НГО земельної ділянки, (грн):":"283407.67","Договір:":"Оренди","Умови  договору, який укладається на земельних торгах:":"  строк 7 років * Переможець аукціону відшкодовує 11011,85 грн.на р/р 26008055023692 в ПАТ КБ «Приватбанк»,              МФО 337546, код ЄДРПОУ 35187108, отримувач ПП «Ромни-Проект»","Стартовий розмір річної плати за користування земельною ділянкою (грн):":"22672.61","Містобудівні умови земельної ділянки:":"не встановлені","Час проведення земельних торгів:":"21.06.2019 09:00","Місце проведення земельних торгів:":"Сумська область,  район,  ;Електронний майданчик ДП «СЕТАМ» https://land.setam.net.ua/auctions/filters/region=18","Обмеження забудови земельної ділянки:":"не встановлені","Розмір реєстраційного внеску:":"960.00","Розмір гарантійного внеску:":"1133.63","Порядок сплати внесків:":"до 18.06.2019 до 09:00 включно","Розмір річної плати за користування земельною ділянкою:":"37296.05","Строк користування земельною ділянкою:":"7"}