{"auctionId":"19746","Посада:":"Начальник юридичного відділу","П.І.П:":"Парокінний Ігор Анатолійович","Контактний телефон:":"(0522)-35-20-59","Отримувач":"Кіровоградська регіональна філія державного підприємства \"Центр державного земельного кадастру\"","Код отримувача (ЄДПРОУ)":"26448548","Банк отримувача для сплати гарантійного внеску":"ПАТ \"КБ\" Приватбанк\"","Код банку отримувача (МФО) для сплати гарантійного внеску":"323583","Рахунок отримувача для сплати гарантійного внеску":"26003052925717","Банк отримувача для сплати реєстраційного внеску":"ПАТ \"Укрексімбанк\" в м. Кропивницькому","Код банку отримувача (МФО) для сплати реєстраційного внеску":"322313","Рахунок отримувача для сплати реєстраційного внеску":"26001000001908","Найменування організатора земельних торгів:":"Головне управління Держгеокадастру у Кіровоградській області оголошує про проведення електронних земельних торгів","Кадастровий номер:":"3524655100:02:000:9101","Місце розташування:":"Кіровоградська область, Онуфріївський район, Онуфріївська селищна рада","Площа земельної ділянки:":"6.0000","Цільове призначення земельної ділянки:":"Для ведення товарного сільськогосподарського виробництва","Містобудівні потреби (види використання):":"відсутні","НГО земельної ділянки, (грн):":"141979.78","Договір:":"Оренди","Умови  договору, який укладається на земельних торгах:":"Договір оренди земельної ділянки строком на 7 років укладається між переможцем та організатором  торгів безпосередньо у день проведення торгів. Детальні умови договору викладені в проекті договору, що додаєтся.","Стартовий розмір річної плати за користування земельною ділянкою (грн):":"11358.38","Містобудівні умови земельної ділянки:":"відсутні ","Час проведення земельних торгів:":"10.09.2019 09:00","Місце проведення земельних торгів:":"Кіровоградська область, Онуфріївський район, с. Омельник;Електронний майданчик державного підприємства \"СЕТАМ\" https://land.setam.net.ua/auction/","Обмеження забудови земельної ділянки:":"відсутні","Розмір реєстраційного внеску:":"1003.50","Розмір гарантійного внеску:":"567.92","Порядок сплати внесків:":"Відповідно до зазначених рахунків до подачі заяви не пізніше 04.09.2019 року до 11:00, заяви подаються через ДП \"СЕТАМ\" https://land.setam.net.ua, витрати на підготовку лоту -6952,03 грн. Переможець відшкодовує виконавцю 50% річної орендної плати.","Розмір річної плати за користування земельною ділянкою:":"37084.25","Строк користування земельною ділянкою:":"7"}