{"auctionId":"20253","Посада:":"Інженер - землевпорядник","П.І.П:":"Сологуб Зоя Іванівна","Контактний телефон:":"+38 (095) 598-51-36 •\tE-mail: torgudzk@gmail.com •\tАдреса: м. Полтава, вул.Зіньківська, 19, офіс 106.","Отримувач":"Полтавська регіональна філія Державного підприємства \"Центр державного земельного кадастру\"","Код отримувача (ЄДПРОУ)":"26458021","Банк отримувача для сплати гарантійного внеску":"АТ КБ \"ПРИВАТБАНК\" (UA603314010000026008054213163)","Код банку отримувача (МФО) для сплати гарантійного внеску":"331401","Рахунок отримувача для сплати гарантійного внеску":"26008054213163","Банк отримувача для сплати реєстраційного внеску":"АТ КБ \"ПРИВАТБАНК\" (UA613314010000026007054208038)","Код банку отримувача (МФО) для сплати реєстраційного внеску":"331401","Рахунок отримувача для сплати реєстраційного внеску":"26007054208038","Найменування організатора земельних торгів:":"Головне управління Держгеокадастру у Подтавській області","Кадастровий номер:":"5323882600:00:012:0034","Місце розташування:":"Полтавська область, Пирятинський район, Дейманівська сільська рада","Площа земельної ділянки:":"20.0000","Цільове призначення земельної ділянки:":"Для ведення товарного сільськогосподарського виробництва","Містобудівні потреби (види використання):":"Відсутні","НГО земельної ділянки, (грн):":"601558.69","Договір:":"Оренди","Умови  договору, який укладається на земельних торгах:":"Термін оренди 7 років. З іншими умовами договору оренди можна ознайомитися у вкладиних файлах. Розмір витрат виконавця земельних торгів, понесиних на підготовку лота до продажу 12088,34 грн.","Стартовий розмір річної плати за користування земельною ділянкою (грн):":"72187.04","Містобудівні умови земельної ділянки:":"Відсутні","Час проведення земельних торгів:":"25.09.2019 09:00","Місце проведення земельних торгів:":"Полтавська область,  район,  ;Електронний майданчик державного підприємства «СЕТАМ» - https://land.setam.net.ua/auction. (Земельні ділянки розташовані за межами населиних пунктів на території Пирятинського району)","Обмеження забудови земельної ділянки:":"Відсутні","Розмір реєстраційного внеску:":"960.50","Розмір гарантійного внеску:":"3609.35","Порядок сплати внесків:":"До 9:00 години 20 вересня 2019 року, заяви подаються через електронний майданчик ДП \"СЕТАМ\" - https://land.setam.net.ua","Розмір річної плати за користування земельною ділянкою:":"190214.42","Строк користування земельною ділянкою:":"7"}