{"auctionId":"20693","Посада:":"Генеральний директор","П.І.П:":"Григор’єв Ігор Григорович","Контактний телефон:":"(0552) 32-53-60, 32-53-61","Отримувач":"Товарна Біржа \"Аграрна Біржа\"","Код отримувача (ЄДПРОУ)":"31390220","Банк отримувача для сплати гарантійного внеску":"АТ \"Райффайзен Банк Аваль\"","Код банку отримувача (МФО) для сплати гарантійного внеску":"380805","Рахунок отримувача для сплати гарантійного внеску":"26000501002","Банк отримувача для сплати реєстраційного внеску":"АТ \"Райффайзен Банк Аваль\"","Код банку отримувача (МФО) для сплати реєстраційного внеску":"380805","Рахунок отримувача для сплати реєстраційного внеску":"26006122151","Найменування організатора земельних торгів:":"Павлівська сільська рада","Кадастровий номер:":"6525483000:01:001:0015","Місце розташування:":"Херсонська область, Чаплинський район, с. Павлівка, вулиця Миру, 5-а","Площа земельної ділянки:":"0.0400","Цільове призначення земельної ділянки:":"03.07","Містобудівні потреби (види використання):":"для будівництва та обслуговування будівель торгівлі","НГО земельної ділянки, (грн):":"97996.27","Договір:":"Купівлі-продажу","Умови  договору, який укладається на земельних торгах:":"ДКП земельної ділянки між організатором та переможцем укладається в день проведення торгів. Переможець сплачує витрати на підготовку лота у сумі 15 000,00 грн. Детальні умови договору викладені у проекті договору, що додається у матеріалах лота.","Стартова ціна продажу земельної ділянки (грн):":"16248.00","Містобудівні умови земельної ділянки:":"Відсутні","Час проведення земельних торгів:":"23.10.2019 11:00","Місце проведення земельних торгів:":"Херсонська область, Чаплинський район, с. Павлівка;вул.Богородицька, 17, каб. 407 приміщення ТБ \"Аграрна Біржа\"","Обмеження забудови земельної ділянки:":"Відсутні","Розмір реєстраційного внеску:":"1003.50","Розмір гарантійного внеску:":"812.40","Порядок сплати внесків:":"Кінцевий термін подання заяви про участь у торгах - до 17.00 год. 17.10.2019 (включно). До заяви додаються документи про сплату реєстраційного і гарантійного внесків на відповідні рахунки виконавця торгів.","Ціна продажу земельної ділянки:":"20310.00"}