{"auctionId":"20926","Посада:":"відповідальна особа","П.І.П:":"Романко Р.М.","Контактний телефон:":"+380509871769","Отримувач":"ФОП Романко Р.М.","Код отримувача (ЄДПРОУ)":"3012518013","Банк отримувача для сплати гарантійного внеску":"АТ \"Ощадбанк\"","Код банку отримувача (МФО) для сплати гарантійного внеску":"356334","Рахунок отримувача для сплати гарантійного внеску":"343563340000026000501481223","Банк отримувача для сплати реєстраційного внеску":"АТ \"Ощадбанк\"","Код банку отримувача (МФО) для сплати реєстраційного внеску":"356334","Рахунок отримувача для сплати реєстраційного внеску":"393563340000026001500481223","Найменування організатора земельних торгів:":"Вашківецька міська рада","Кадастровий номер:":"7320510400:04:001:0213","Місце розташування:":"Чернівецька область, Вижницький район, с.Волока","Площа земельної ділянки:":"4.2782","Цільове призначення земельної ділянки:":"Для ведення товарного сільськогосподарського виробництва","Містобудівні потреби (види використання):":"для ведення товарного сільськогосподарського виробництва","НГО земельної ділянки, (грн):":"7406.03","Договір:":"Оренди","Умови  договору, який укладається на земельних торгах:":"термін оренди 7 років","Стартовий розмір річної плати за користування земельною ділянкою (грн):":"592.48","Містобудівні умови земельної ділянки:":"використовувати за цільовим призначенням","Час проведення земельних торгів:":"31.10.2019 11:00","Місце проведення земельних торгів:":"Чернівецька область, Вижницький район, с. Волока;м. Вашківці, вул. Героїв Майдану, 2 (приміщення міської ради)","Обмеження забудови земельної ділянки:":"відсутні","Розмір реєстраційного внеску:":"1003.00","Розмір гарантійного внеску:":"29.62","Порядок сплати внесків:":"1. «Реєстраційний внесок 1003,00 грн., в т.ч.ПДВ-20%»; 2. «Гарантійний внесок 29,62 грн. без ПДВ ». Прийом заяв та документів до 15.00 год. до 25.10.2019р. включно","Розмір річної плати за користування земельною ділянкою:":"604.32","Строк користування земельною ділянкою:":"7"}