{"auctionId":"2741","Посада:":"директор","П.І.П:":"Булах Руслан Анатолійович","Контактний телефон:":"(0472)63-09-18,63-07-45,63-08-06,067-957-96-51","Отримувач":"Товарна Біржа Агропромислового Комплексу Центральних областей України","Код отримувача (ЄДПРОУ)":"33282885","Банк отримувача для сплати гарантійного внеску":"ЦФ ПАТ \"Кредобанк\"","Код банку отримувача (МФО) для сплати гарантійного внеску":"325365","Рахунок отримувача для сплати гарантійного внеску":"2600301460464","Банк отримувача для сплати реєстраційного внеску":"ЦФ ПАТ \"Кредобанк\"","Код банку отримувача (МФО) для сплати реєстраційного внеску":"325365","Рахунок отримувача для сплати реєстраційного внеску":"2600301460464","Найменування організатора земельних торгів:":"Катеринопільська селищна рада, Катеринопільського району, Черкаської області","Кадастровий номер:":"7122255100:01:002:0307","Місце розташування:":"Черкаська область, Катеринопільський район, смт. Катеринопіль, вулиця Карла Маркса, 18-в","Площа земельної ділянки:":"0.0060","Цільове призначення земельної ділянки:":"Для будівництва та обслуговування будівель торгівлі","Містобудівні потреби (види використання):":"Землі житлової та громадської забудови (для будівництва та обслуговування будівель торгівлі).","Договір:":"Оренди","Умови  договору, який укладається на земельних торгах:":"Право оренди надається  на 10 років. Передача земельної ділянки в оренду здійснються після державної реєстрації договору на підставі акту приймання- передачі.","Стартовий розмір річної плати за користування земельною ділянкою (грн):":"864.36","Містобудівні умови земельної ділянки:":"Для будівництва та обслуговування будівель торгівлі","Час проведення земельних торгів:":"25.06.2015 12:00","Місце проведення земельних торгів:":"Черкаська область, Черкаси район, м. Черкаси;вул.Смілянська,131, офіс 329, 18000, м.Черкаси, ел.пошта tovagrobiga@gmail.com","Обмеження забудови земельної ділянки:":"відсутні","Розмір реєстраційного внеску:":"300.00","Розмір гарантійного внеску:":"43.22","Порядок сплати внесків:":"Термін оплати внесків до 19 червня 2015 року","Розмір річної плати за користування земельною ділянкою:":"881.64","Строк користування земельною ділянкою:":"10"}