{"auctionId":"21621","Посада:":"Ліцетатор","П.І.П:":"Коломієць Андрій Олександрович","Контактний телефон:":"(050) 304-50-04 •\tE-mail: torgy.dpzempro@ukr.net •\tАдреса: 36039, Полтавська обл., місто Полтава, вул. Крамського, 9.","Отримувач":"Державне підприємство \"Полтавський науково-дослідний та проектний інститут землеустрою\"","Код отримувача (ЄДПРОУ)":"00689214","Банк отримувача для сплати гарантійного внеску":"ПАТ «КРЕДІ АГРІКОЛЬ БАНК»","Код банку отримувача (МФО) для сплати гарантійного внеску":"300614","Рахунок отримувача для сплати гарантійного внеску":"UA263006140000026007500336952","Банк отримувача для сплати реєстраційного внеску":"ПАТ «КРЕДІ АГРІКОЛЬ БАНК»","Код банку отримувача (МФО) для сплати реєстраційного внеску":"300614","Рахунок отримувача для сплати реєстраційного внеску":"UA593006140000026008000000624","Найменування організатора земельних торгів:":"Головне управління Держгеокадастру у Полтавській області","Кадастровий номер:":"5324580800:00:003:0468","Місце розташування:":"Полтавська область, Семенівський район, на території Василівської сільської ради","Площа земельної ділянки:":"22.0000","Цільове призначення земельної ділянки:":"01.01 (длдя ведення товарного сільськогосподарського виробництва).","Містобудівні потреби (види використання):":"Відсутні","НГО земельної ділянки, (грн):":"155128.48","Договір:":"Оренди","Умови  договору, який укладається на земельних торгах:":"Термін оренди 7 років. З іншими умовами договору оренди можна ознайомитися у вкладиних файлах. Розмір витрат виконавця земельних торгів, понесиних на підготовку лота до продажу 16047,80 грн.","Стартовий розмір річної плати за користування земельною ділянкою (грн):":"15512.85","Містобудівні умови земельної ділянки:":"Відсутні","Час проведення земельних торгів:":"04.12.2019 10:00","Місце проведення земельних торгів:":"Полтавська область, Полтава район, м. Полтава;вул. Уютна, 23. (Приміщення Головного управління Держгеокадастру у Полтавської області). (Земельні ділянки розташовані за межами населених пунктів на території Семенівського району).","Обмеження забудови земельної ділянки:":"Відсутні","Розмір реєстраційного внеску:":"960.50","Розмір гарантійного внеску:":"775.64","Порядок сплати внесків:":"До 17:00 години «28» листопада 2019 р.","Розмір річної плати за користування земельною ділянкою:":"15745.54","Строк користування земельною ділянкою:":"7"}