{"auctionId":"22219","Посада:":"Завідуючий сектором із організації та проведення земельних торгів","П.І.П:":"Волошина Людмила Сергіївна","Контактний телефон:":"(04747) 6-23-92","Отримувач":"ПП «Земекспертцентр»","Код отримувача (ЄДПРОУ)":"36213615","Банк отримувача для сплати гарантійного внеску":"АТ «Райффайзен Банк Аваль»","Код банку отримувача (МФО) для сплати гарантійного внеску":"380805","Рахунок отримувача для сплати гарантійного внеску":"UA623808050000000026000533779","Банк отримувача для сплати реєстраційного внеску":"ЧГР ПАТ КБ «Приватбанк»","Код банку отримувача (МФО) для сплати реєстраційного внеску":"354347","Рахунок отримувача для сплати реєстраційного внеску":"UA503543470000026005060283175","Найменування організатора земельних торгів:":"ІВАНЬКІВСЬКА СІЛЬСЬКА РАДА Маньківського району Черкаської області ","Кадастровий номер:":"7123182501:01:002:0100","Місце розташування:":"Черкаська область, Маньківський район, територія Іваньківської сільської територіальної громади (в межах населеного пункту)","Площа земельної ділянки:":"20.1000","Цільове призначення земельної ділянки:":"10.07","Містобудівні потреби (види використання):":"Відсутні","НГО земельної ділянки, (грн):":"10815810.00","Договір:":"Оренди","Умови  договору, який укладається на земельних торгах:":"Строк оренди – 15 років. Переможець сплачує вартість витрат на підготовку лота у сумі 32146,57 грн. та винагороду виконавцю у розмірі 50% річної плати за користування зем. діл., але не більше 2000 неоподаткованих мінімумів доходів громадян","Стартовий розмір річної плати за користування земельною ділянкою (грн):":"50077.20","Містобудівні умови земельної ділянки:":"Відсутні","Час проведення земельних торгів:":"19.12.2019 11:00","Місце проведення земельних торгів:":"Черкаська область, Маньківський район, с. Іваньки;м. Жашків, вул. Соборна, 58-а, Черкаська обл.","Обмеження забудови земельної ділянки:":"Відсутні","Розмір реєстраційного внеску:":"960.00","Розмір гарантійного внеску:":"2503.86","Порядок сплати внесків:":"до 16:00 год. 13 грудня 2019 р.","Розмір річної плати за користування земельною ділянкою:":"50327.59","Строк користування земельною ділянкою:":"15"}