{"auctionId":"22579","Посада:":"провідний юрист юридичного відділу","П.І.П:":"Шевченко Анна Леонідівна","Контактний телефон:":"(0472) 63-76-67","Отримувач":"ДП « Черкаський науково-дослідний та проектний інститут землеустрою»","Код отримувача (ЄДПРОУ)":"00709709","Банк отримувача для сплати гарантійного внеску":"АТ «УкрСиббанк»","Код банку отримувача (МФО) для сплати гарантійного внеску":"351005","Рахунок отримувача для сплати гарантійного внеску":"UA133510050000026003041468403","Банк отримувача для сплати реєстраційного внеску":"АТ «УкрСиббанк»","Код банку отримувача (МФО) для сплати реєстраційного внеску":"351005","Рахунок отримувача для сплати реєстраційного внеску":"UA313510050000026002041468404","Найменування організатора земельних торгів:":"Головне управління Держгеокадастру в Черкаській області","Кадастровий номер:":"7125782000:02:001:0340","Місце розташування:":"Черкаська область, Шполянський район, Водянська сільська рада","Площа земельної ділянки:":"9.9149","Цільове призначення земельної ділянки:":"Для ведення товарного сільськогосподарського виробництва","Містобудівні потреби (види використання):":"-","НГО земельної ділянки, (грн):":"116658.35","Договір:":"Оренди","Умови  договору, який укладається на земельних торгах:":"Строк оренди – 7 років.  Переможець торгів сплачує виконавцю вартість витрат на підготовку лота у сумі 7104,83 грн. та винагороду у розмірі 50% річної плати за користування зем. діл., але не більше як 2000 неоподаткованих мінімумів доходів громадян.","Стартовий розмір річної плати за користування земельною ділянкою (грн):":"9332.67","Містобудівні умови земельної ділянки:":"-","Час проведення земельних торгів:":"20.01.2020 10:00","Місце проведення земельних торгів:":"Черкаська область, Черкаси район, м. Черкаси;вул. Смілянська, 118, кімната № 17","Обмеження забудови земельної ділянки:":"-","Розмір реєстраційного внеску:":"900.00","Розмір гарантійного внеску:":"466.63","Порядок сплати внесків:":"14.01.2020 до 16:00 год.","Розмір річної плати за користування земельною ділянкою:":"9472.65","Строк користування земельною ділянкою:":"7"}