{"auctionId":"22693","Посада:":"Ліцитатор","П.І.П:":"Вороніна Олена Владиславівна","Контактний телефон:":"(0629) 41-61-47, 0990566473, 0672905767(06272) 6-13-28, +380996157927","Отримувач":"ПП \" Оршад\"","Банк отримувача для сплати гарантійного внеску":"ПАТ «АЛЬФА-БАНК»","Код банку отримувача (МФО) для сплати гарантійного внеску":"300346","Рахунок отримувача для сплати гарантійного внеску":"UA 63 300346 0000026009016933902","Банк отримувача для сплати реєстраційного внеску":"ПАТ «АЛЬФА-БАНК»","Код банку отримувача (МФО) для сплати реєстраційного внеску":"300346","Рахунок отримувача для сплати реєстраційного внеску":"UA103003460000026000016933901","Найменування організатора земельних торгів:":"Головне управління Держгеокадастру у Донецькій області","Кадастровий номер:":"1422786500:11:000:0322","Місце розташування:":"Донецька область, Покровський район, Срібненська сільська рада","Площа земельної ділянки:":"13.6902","Цільове призначення земельної ділянки:":"Для ведення товарного сільськогосподарського виробництва","Містобудівні потреби (види використання):":"відсутні","НГО земельної ділянки, (грн):":"93957.57","Договір:":"Оренди","Умови  договору, який укладається на земельних торгах:":"\r\nзгідно типового договору оренди, що додається","Стартовий розмір річної плати за користування земельною ділянкою (грн):":"8456.18","Містобудівні умови земельної ділянки:":"відсутні","Час проведення земельних торгів:":"14.01.2020 11:00","Місце проведення земельних торгів:":"Донецька область, Красноармійськ район, м. Красноармійськ;Донецька область, м.Покровськ, вул.Торгівельна, 11, адміністративна будівля","Обмеження забудови земельної ділянки:":"відсутні","Розмір реєстраційного внеску:":"1051.00","Розмір гарантійного внеску:":"0.00","Порядок сплати внесків:":"порядок сплати внесків (сплачується з відкритого в банку рахунку ): призначення платежу : 1.Реєстраційний внесок 1051,00 грн., без ПДВ», 2. «Гарантійний внесок 422,81 грн. без ПДВ. прийом заяв та документів з 09.00 до 17.00 до 08.01.2020 включно.\r\n","Розмір річної плати за користування земельною ділянкою:":"9428.62","Строк користування земельною ділянкою:":"7"}