{"auctionId":"25847","Посада:":"Директор","П.І.П:":"Дзібій Мирон Васильович","Контактний телефон:":"0503887323","Отримувач":"Товарна Біржа \"Західна-Універсальна\"","Код отримувача (ЄДПРОУ)":"35022850","Банк отримувача для сплати гарантійного внеску":"АТ Райффайзен банк \"Аваль\"","Код банку отримувача (МФО) для сплати гарантійного внеску":"380805","Рахунок отримувача для сплати гарантійного внеску":"UA643808050000000026004491828","Банк отримувача для сплати реєстраційного внеску":"АТ Райффайзен банк \"Аваль\"","Код банку отримувача (МФО) для сплати реєстраційного внеску":"380805","Рахунок отримувача для сплати реєстраційного внеску":"UA343808050000000026006115469","Найменування організатора земельних торгів:":"Задністрянська  сільська  рада ","Кадастровий номер:":"2621283201:01:001:0657","Місце розташування:":"Івано-Франківська область, Галицький район, с.Задністрянське, вулиця Львівська, 4б","Площа земельної ділянки:":"0.2534","Цільове призначення земельної ділянки:":"03.10","Містобудівні потреби (види використання):":"для будівництва та обслуговування будівель ринкової інфраструктури  (адміністративних будинків, офісних приміщень та інших будівель громадської забудови, які використовуються для здійснення підприємницької та іншої діяльності , пов’язаної з отриманням при","НГО земельної ділянки, (грн):":"277475.63","Договір:":"Оренди","Умови  договору, який укладається на земельних торгах:":"Переможець аукціону зобов’язується відшкодувати вартість послуг з проведення земельних торгів.","Стартовий розмір річної плати за користування земельною ділянкою (грн):":"33297.08","Містобудівні умови земельної ділянки:":"згідно відповідних висновків","Час проведення земельних торгів:":"09.07.2020 12:00","Місце проведення земельних торгів:":"Івано-Франківська область, Івано-Франківськ район, м. Івано-Франківськ;вул. Грушевського,11, ","Обмеження забудови земельної ділянки:":"згідно відповідних висновків","Розмір реєстраційного внеску:":"1050.00","Розмір гарантійного внеску:":"9989.12","Порядок сплати внесків:":"1) Реєстраційний внесок – 1050 грн.00 коп.  ;\r\n 2) Гарантійний внесок – 9989 грн 12 коп.; \r\n\r\nПрийом заяв разом з документами про сплату  внесків  до 03-07-2020 р, до15-00 год.  за адресою: м. Івано-Франківськ, вул. Грушевського,11, каб.213, тел..05038873","Розмір річної плати за користування земельною ділянкою:":"33796.55","Строк користування земельною ділянкою:":"49"}