{"auctionId":"26345","Посада:":"ліцитатор","П.І.П:":"Покотило Анатолій Миколайович","Контактний телефон:":"050 343-28-31","Отримувач":"ПП \"РЕАЛ-Т\"","Код отримувача (ЄДПРОУ)":"34469900","Банк отримувача для сплати гарантійного внеску":"АТ \"УкрСиббанк\"","Код банку отримувача (МФО) для сплати гарантійного внеску":"351005","Рахунок отримувача для сплати гарантійного внеску":"UA683510050000026000054184700","Банк отримувача для сплати реєстраційного внеску":"АТ \"УкрСиббанк\"","Код банку отримувача (МФО) для сплати реєстраційного внеску":"351005","Рахунок отримувача для сплати реєстраційного внеску":"UA683510050000026000054184700","Найменування організатора земельних торгів:":" Старомерчицька селищна рада, Харківська область, Валківський район, ","Кадастровий номер:":"6321256000:00:001:0238","Місце розташування:":"Харківська область, Валківський район, селище Старий Мерчик, вулиця Центральна, біля автозупинки","Площа земельної ділянки:":"0.0033","Цільове призначення земельної ділянки:":"16.00","Містобудівні потреби (види використання):":"згідно документації із землеустрою","НГО земельної ділянки, (грн):":"20100.30","Договір:":"Оренди","Умови  договору, який укладається на земельних торгах:":"Строк користування земельною ділянкою 15 років. Переможцем торгів сплачуються витрати на підготовку лота у сумі 8000.00 грн. та винагорода виконавцю торгів 50% від річної орендної плати, але не більше 2000 неоподатковуваних мінімумів доходів громадян","Стартовий розмір річної плати за користування земельною ділянкою (грн):":"2412.04","Містобудівні умови земельної ділянки:":"згідно документації із землеустрою","Час проведення земельних торгів:":"28.07.2020 11:00","Місце проведення земельних торгів:":"Харківська область, Валківський район, с.м.т. Старий Мерчик;вул. Центральна, 5 (приміщення селищної ради)","Обмеження забудови земельної ділянки:":"згідно документації із землеустрою","Розмір реєстраційного внеску:":"1051.00","Розмір гарантійного внеску:":"723.61","Порядок сплати внесків:":"до 22 липня 2020року","Причина:":"Відсутність учасників або наявність тільки одного учасника"}