{"auctionId":"26829","Посада:":"в.о.директора","П.І.П:":"Риженкова А.В.","Контактний телефон:":"0502689298","Отримувач":"ДП \"Дніпровський науково-дослідний та проектний інститут землеустрою\"","Код отримувача (ЄДПРОУ)":"00689177","Банк отримувача для сплати гарантійного внеску":"ПАТ КБ \"ПриватБанк\"","Код банку отримувача (МФО) для сплати гарантійного внеску":"305299","Рахунок отримувача для сплати гарантійного внеску":"UA423052990000026004050251132","Банк отримувача для сплати реєстраційного внеску":"ПАТ КБ \"ПриватБанк\"","Код банку отримувача (МФО) для сплати реєстраційного внеску":"305299","Рахунок отримувача для сплати реєстраційного внеску":"UA423052990000026004050251132","Найменування організатора земельних торгів:":"Виконавчий комітет Новопокровської сільської ради","Кадастровий номер:":"1225055400:01:035:0014","Місце розташування:":"Дніпропетровська область, Солонянський район, Новопокроваська селищна рада","Площа земельної ділянки:":"7.6759","Цільове призначення земельної ділянки:":"Для ведення товарного сільськогосподарського виробництва","Містобудівні потреби (види використання):":"-","НГО земельної ділянки, (грн):":"233783.60","Договір:":"Оренди","Умови  договору, який укладається на земельних торгах:":"продаж права оренди на земельну ділянку , термін оренди 25 років, переможець повинен відшкодувати витрати на організацію та проведення земельного аукціону, які складають 22 000,00 грн","Стартовий розмір річної плати за користування земельною ділянкою (грн):":"18702.38","Містобудівні умови земельної ділянки:":"-","Час проведення земельних торгів:":"20.08.2020 11:00","Місце проведення земельних торгів:":"Дніпропетровська область, Дніпровський район,  ;смт.Слобожанське вул. В.Сухомлинського,42  ДП \"Дніпровський науково-дослідний та проектний інститут землеустрою\" 7-й поверх","Обмеження забудови земельної ділянки:":"відсутні","Розмір реєстраційного внеску:":"1003.50","Розмір гарантійного внеску:":"5610.71","Порядок сплати внесків:":"реєстраційні та гарантійні внески сплачуються на зазначені рахунки виконавця торгів, останній день прийому заяв з документами не пізніше ніж за три робочі дні до дати проведення торгів"}