{"auctionId":"3396","Посада:":"Генеральний директор","П.І.П:":"Крамаренко Леонід Віталійович","Контактний телефон:":"0522245822","Отримувач":"Кіровоградська Аграрна Біржа","Код отримувача (ЄДПРОУ)":"31008446","Банк отримувача для сплати гарантійного внеску":"ЦП ВАТ Кредобанк, м. Львів","Код банку отримувача (МФО) для сплати гарантійного внеску":"325365","Рахунок отримувача для сплати гарантійного внеску":"2600601899054","Банк отримувача для сплати реєстраційного внеску":"ЦП ВАТ Кредобанк, м. Львів","Код банку отримувача (МФО) для сплати реєстраційного внеску":"325365","Рахунок отримувача для сплати реєстраційного внеску":"2600702899054","Найменування організатора земельних торгів:":"Тальнівська міська рада Черкаської області","Кадастровий номер:":"7124010100:03:002:2715","Місце розташування:":"Черкаська область, Тальнівський район, м. Тальне, на автошляху Золотоноша-Черкаси-Сміла-Умань 178км+65м","Площа земельної ділянки:":"0.4013","Цільове призначення земельної ділянки:":"для будівництва та обслуговування будівель торгівлі","Містобудівні потреби (види використання):":"для будівництва та обслуговування будівель торгівлі","Договір:":"Оренди","Умови  договору, який укладається на земельних торгах:":"продажу права оренди терміном на 49 років","Стартовий розмір річної плати за користування земельною ділянкою (грн):":"31713.13","Містобудівні умови земельної ділянки:":"відсутні","Час проведення земельних торгів:":"08.10.2015 11:00","Місце проведення земельних торгів:":"Черкаська область, Тальнівський район, м. Тальне;Черкаська область,Тальнівський район, м Тальне; 20400, вул. Гагаріна 8 (приміщення міського Центру культури та дозвілля)","Обмеження забудови земельної ділянки:":"відсутні","Розмір реєстраційного внеску:":"609.00","Розмір гарантійного внеску:":"1585.66","Порядок сплати внесків:":"Кінцевий термін сплати внесків до 02.10.2015 року включно","Розмір річної плати за користування земельною ділянкою:":"31871.70","Строк користування земельною ділянкою:":"49"}