{"auctionId":"28486","Посада:":"ліцитатор","П.І.П:":"Калачинська Олена Василівна","Контактний телефон:":"0332-24-64-64  ( 0503398598,   0503398597)","Отримувач":"ТзОВ «Олді»","Код отримувача (ЄДПРОУ)":"30733279","Банк отримувача для сплати гарантійного внеску":"\"Приватбанк\", м. Луцьк","Код банку отримувача (МФО) для сплати гарантійного внеску":"303440","Рахунок отримувача для сплати гарантійного внеску":"593034400000026003055500578","Банк отримувача для сплати реєстраційного внеску":"\"Приватбанк\", м. Луцьк","Код банку отримувача (МФО) для сплати реєстраційного внеску":"303440","Рахунок отримувача для сплати реєстраційного внеску":"563034400000026002233016001","Найменування організатора земельних торгів:":"Ківерцівська міська рада","Кадастровий номер:":"0721886800:05:000:1484","Місце розташування:":"Волинська область, Ківерцівський район, Ківерцівська міська рада","Площа земельної ділянки:":"17.8929","Цільове призначення земельної ділянки:":"A.01.01","Містобудівні потреби (види використання):":"для ведення товарного сільськогосподарського  виробництва","НГО земельної ділянки, (грн):":"252167.07","Договір:":"Оренди","Умови  договору, який укладається на земельних торгах:":"10 років. Договір оренди земельної ділянки укладається між організатором земельних торгів і переможцем безпосередньо в день проведення торгів (з умовами договору можна ознайомитись у вкладених файлах)","Стартовий розмір річної плати за користування земельною ділянкою (грн):":"30260.05","Містобудівні умови земельної ділянки:":"відсутні","Час проведення земельних торгів:":"23.10.2020 10:30","Місце проведення земельних торгів:":"Волинська область, Ківерцівський район, м. Ківерці;вул. Киричука,1","Обмеження забудови земельної ділянки:":"відсутні","Розмір реєстраційного внеску:":"1098.50","Розмір гарантійного внеску:":"9078.01","Порядок сплати внесків:":"До 16 год. 00 хв.19.10.2020 року (включно). Переможцем торгів сплачуються кошти: за підготовку лота в сумі 8 908,33 грн.; за організацію та проведення торгів 50 % від вартості продажу лота (детальніше дивитись інформацію у вкладених файлах)","Розмір річної плати за користування земельною ділянкою:":"30713.95","Строк користування земельною ділянкою:":"10"}