{"auctionId":"29162","Посада:":"відповідальна особа","П.І.П:":"Гамаль А.В.","Контактний телефон:":"+380991854885","Отримувач":"Чернівецька філія ДП \"Вінницький науково-дослідний та проектний інститут землеустрою\"","Код отримувача (ЄДПРОУ)":"43669538","Банк отримувача для сплати гарантійного внеску":"АБ \"Укргазбанк\"","Код банку отримувача (МФО) для сплати гарантійного внеску":"320478","Рахунок отримувача для сплати гарантійного внеску":"UA823204780000026000924890019","Банк отримувача для сплати реєстраційного внеску":"АБ \"Укргазбанк\"","Код банку отримувача (МФО) для сплати реєстраційного внеску":"320478","Рахунок отримувача для сплати реєстраційного внеску":"UA823204780000026000924890019","Найменування організатора земельних торгів:":"Головне управління Держгеокадастру у Чернівецькій області","Кадастровий номер:":"7320584000:01:002:0087","Місце розташування:":"Чернівецька область, Вижницький район, Лукавецька сільська рада","Площа земельної ділянки:":"10.0000","Цільове призначення земельної ділянки:":"Для ведення товарного сільськогосподарського виробництва","Містобудівні потреби (види використання):":"Для ведення товарного сільськогосподарського виробництва","НГО земельної ділянки, (грн):":"117801.06","Договір:":"Оренди","Умови  договору, який укладається на земельних торгах:":"Договір укладається на 7 років","Стартовий розмір річної плати за користування земельною ділянкою (грн):":"9424.08","Містобудівні умови земельної ділянки:":"Використовувати за цільовим призначенням.","Час проведення земельних торгів:":"24.11.2020 00:00","Місце проведення земельних торгів:":"Чернівецька область, Вижницький район, с. Лукавці;вул.Героїв Майдану, 194-А, приміщення Головного управління Держгеокадастру у Чернівецькій області","Обмеження забудови земельної ділянки:":"водоохоронна зона на площі 0,3215га","Розмір реєстраційного внеску:":"1098.00","Розмір гарантійного внеску:":"2827.22","Порядок сплати внесків:":"1. «Реєстраційний внесок 1098,00 грн., в т.ч.ПДВ-20%»; 2. «Гарантійний внесок 2827.22 грн. без ПДВ ». Прийом заяв та документів до 16.30 год. до 18.11.2020р. включно","Розмір річної плати за користування земельною ділянкою:":"9612.56","Строк користування земельною ділянкою:":"7"}