{"auctionId":"29502","Посада:":"відповідальна особа","П.І.П:":"Козьмук А.П.","Контактний телефон:":"+380505413929","Отримувач":"ТзОВ \"Глобус КО\"","Код отримувача (ЄДПРОУ)":"36945702","Банк отримувача для сплати гарантійного внеску":"ЧФ АТ КБ \"Приватбанк\"","Код банку отримувача (МФО) для сплати гарантійного внеску":"356282","Рахунок отримувача для сплати гарантійного внеску":"UA663562820000026000051512208","Банк отримувача для сплати реєстраційного внеску":"ЧФ АТ КБ \"Приватбанк\"","Код банку отримувача (МФО) для сплати реєстраційного внеску":"356282","Рахунок отримувача для сплати реєстраційного внеску":"UA873562820000026000051510084","Найменування організатора земельних торгів:":"Головне управління Держгеокадастру у Чернівецькій області","Кадастровий номер:":"7320786000:01:003:0132","Місце розташування:":"Чернівецька область, Герцаївський район, Хряцьківська сільська рада","Площа земельної ділянки:":"8.0000","Цільове призначення земельної ділянки:":"Для ведення товарного сільськогосподарського виробництва","Містобудівні потреби (види використання):":"для ведення товарного сільськогосподарського виробництва","НГО земельної ділянки, (грн):":"21813.06","Договір:":"Оренди","Умови  договору, який укладається на земельних торгах:":"термін оренди 7 років","Стартовий розмір річної плати за користування земельною ділянкою (грн):":"1745.04","Містобудівні умови земельної ділянки:":"використовувати за цільовим призначенням","Час проведення земельних торгів:":"08.12.2020 10:00","Місце проведення земельних торгів:":"Чернівецька область, Герцаївський район, с. Хряцька;м. Чернівці, вул. Героїв Майдану 194а (приміщення Головного управління Держгеокадастру у Чернівецькій області)","Обмеження забудови земельної ділянки:":"відсутні","Розмір реєстраційного внеску:":"1098.00","Розмір гарантійного внеску:":"523.51","Порядок сплати внесків:":"1. «Реєстраційний внесок 1098,00грн.»; 2. «Гарантійний внесок 523,51 грн. ». Прийом заяв та документів до 15-00год. 02.12.2020р. включно","Розмір річної плати за користування земельною ділянкою:":"4006.11","Строк користування земельною ділянкою:":"7"}