{"auctionId":"31921","Посада:":"директор","П.І.П:":"Петренко Сергій Анатолійович","Контактний телефон:":"067-445-67-32","Отримувач":"ФОП Петренко С.А","Код отримувача (ЄДПРОУ)":"2909809395","Банк отримувача для сплати гарантійного внеску":"ПАТ КБ \"Приватбанк\"","Код банку отримувача (МФО) для сплати гарантійного внеску":"305299","Рахунок отримувача для сплати гарантійного внеску":"UA083052990000026007000100508","Банк отримувача для сплати реєстраційного внеску":"ПАТ КБ \"Приватбанк\"","Код банку отримувача (МФО) для сплати реєстраційного внеску":"305299","Рахунок отримувача для сплати реєстраційного внеску":"UA913052990000026002020106695","Найменування організатора земельних торгів:":"Головне управління Держгеокадастру у Київській області","Кадастровий номер:":"3221083000:10:001:0003","Місце розташування:":"Київська область, Бородянський район, Качалівська сільська рада","Площа земельної ділянки:":"12.3702","Цільове призначення земельної ділянки:":"Для ведення товарного сільськогосподарського виробництва","Містобудівні потреби (види використання):":"Для ведення товарного сільськогосподарського виробництва","НГО земельної ділянки, (грн):":"113164.05","Договір:":"Оренди","Умови  договору, який укладається на земельних торгах:":"Строк оренди-7 років; витрати на підготовку, організацію, проведення торгів-18000 грн.,винагорода, орендна плата сплачуються переможцем не пізніше трьох банківських днів з дня укладення договору оренди.(ст.135 ЗКУ)","Стартовий розмір річної плати за користування земельною ділянкою (грн):":"13579.69","Містобудівні умови земельної ділянки:":"згідно проекту землеустрою","Час проведення земельних торгів:":"29.03.2021 11:00","Місце проведення земельних торгів:":"Київська область, Бородянський район,  ;03115, м. Київ, вул. Серпова, 3/14 (5-й поверх, актова зала)\r\n","Обмеження забудови земельної ділянки:":"згідно проекту землеустрою","Розмір реєстраційного внеску:":"1100.00","Розмір гарантійного внеску:":"4073.91","Порядок сплати внесків:":"одноразовий платіж","Причина:":"Відсутність учасників або наявність тільки одного учасника"}