{"auctionId":"4084","Посада:":"Заступник директора","П.І.П:":"Цифуляк Оксана Іванівна","Контактний телефон:":"(032) 244-30-92, +380961315421","Отримувач":"ПП \"Фірма \"СОМГІЗ\"","Код отримувача (ЄДПРОУ)":"20810095","Банк отримувача для сплати гарантійного внеску":"ПАТ \"ВіЕс Банк\"","Код банку отримувача (МФО) для сплати гарантійного внеску":"325213","Рахунок отримувача для сплати гарантійного внеску":"26000000013209","Банк отримувача для сплати реєстраційного внеску":"ПАТ \"ВіЕс Банк\"","Код банку отримувача (МФО) для сплати реєстраційного внеску":"325213","Рахунок отримувача для сплати реєстраційного внеску":"26004000001347","Найменування організатора земельних торгів:":"Богородчанська селищна рада","Кадастровий номер:":"2620455100:01:001:1276","Місце розташування:":"Івано-Франківська область, Богородчанський район, смт.Богородчани, вулиця Шевченка (біля будинку №46)","Площа земельної ділянки:":"0.0221","Цільове призначення земельної ділянки:":"В 03.07 для будівництва та обслуговування будівель торгівлі","Містобудівні потреби (види використання):":"для будівництва та обслуговування дитячого торгово-розважального центру з офісними приміщеннями.","Договір:":"Оренди","Умови  договору, який укладається на земельних торгах:":"продаж права оренди","Стартовий розмір річної плати за користування земельною ділянкою (грн):":"4096.56","Містобудівні умови земельної ділянки:":"згідно відповідних висновків","Час проведення земельних торгів:":"20.01.2016 15:00","Місце проведення земельних торгів:":"Івано-Франківська область, Богородчанський район, с.м.т. Богородчани;вул.Грушевського,3","Обмеження забудови земельної ділянки:":"згідно відповідних висновків","Розмір реєстраційного внеску:":"689.00","Розмір гарантійного внеску:":"204.83","Порядок сплати внесків:":"з відкритого в банку рахунку: призначення платежу: 1. «Реєстраційний внесок  689,00грн., в т.ч.ПДВ-20%»;  2. «Гарантійний внесок 204,83грн. без ПДВ ». Прийом заяв та документів з 12.30 до 16.30 год. до 14.01.16р. включно.","Розмір річної плати за користування земельною ділянкою:":"6809.50","Строк користування земельною ділянкою:":"3"}